{
  "initial_board": [
    "00000000",
    "00000000",
    "00000000",
    "10000000",
    "00000000",
    "00000000",
    "00000000",
    "0X000001"
  ],
  "blocked_positions": [
    [
      7,
      1
    ]
  ],
  "placed_queens": [
    [
      3,
      0
    ],
    [
      7,
      7
    ]
  ],
  "solution": [
    [
      3,
      0
    ],
    [
      7,
      7
    ],
    [
      0,
      5
    ],
    [
      1,
      3
    ],
    [
      2,
      6
    ],
    [
      4,
      2
    ],
    [
      5,
      4
    ],
    [
      6,
      1
    ]
  ],
  "complexity": 3
}