{
  "initial_board": [
    "00000000",
    "00000000",
    "00000000",
    "00000000",
    "00000000",
    "00100000",
    "10X0X00X",
    "00000000"
  ],
  "blocked_positions": [
    [
      6,
      4
    ],
    [
      6,
      7
    ],
    [
      6,
      2
    ]
  ],
  "placed_queens": [
    [
      5,
      2
    ],
    [
      6,
      0
    ]
  ],
  "solution": [
    [
      5,
      2
    ],
    [
      6,
      0
    ],
    [
      0,
      4
    ],
    [
      1,
      1
    ],
    [
      2,
      3
    ],
    [
      3,
      5
    ],
    [
      4,
      7
    ],
    [
      7,
      6
    ]
  ],
  "complexity": 4
}