{
  "initial_board": [
    "0000000X",
    "00000000",
    "00000000",
    "00001000",
    "0000X000",
    "00000000",
    "00000000",
    "X0000000"
  ],
  "blocked_positions": [
    [
      7,
      0
    ],
    [
      4,
      4
    ],
    [
      0,
      7
    ]
  ],
  "placed_queens": [
    [
      3,
      4
    ]
  ],
  "solution": [
    [
      3,
      4
    ],
    [
      0,
      2
    ],
    [
      1,
      0
    ],
    [
      2,
      6
    ],
    [
      4,
      7
    ],
    [
      5,
      1
    ],
    [
      6,
      3
    ],
    [
      7,
      5
    ]
  ],
  "complexity": 3
}